{
	"configurations" : 
	[
		{
			"directories" : 
			[
				{
					"build" : ".",
					"jsonFile" : "directory-.-Debug-f5ebdc15457944623624.json",
					"minimumCMakeVersion" : 
					{
						"string" : "3.26"
					},
					"projectIndex" : 0,
					"source" : ".",
					"targetIndexes" : 
					[
						0
					]
				}
			],
			"name" : "Debug",
			"projects" : 
			[
				{
					"directoryIndexes" : 
					[
						0
					],
					"name" : "2514__Count_Anagrams",
					"targetIndexes" : 
					[
						0
					]
				}
			],
			"targets" : 
			[
				{
					"directoryIndex" : 0,
					"id" : "2514__Count_Anagrams::@6890427a1f51a3e7e1df",
					"jsonFile" : "target-2514__Count_Anagrams-Debug-157ff45b2cbdd32cfb53.json",
					"name" : "2514__Count_Anagrams",
					"projectIndex" : 0
				}
			]
		}
	],
	"kind" : "codemodel",
	"paths" : 
	{
		"build" : "/Users/ryanpionee2/Github/Leetcode/2501~3000/2514. Count Anagrams/cmake-build-debug",
		"source" : "/Users/ryanpionee2/Github/Leetcode/2501~3000/2514. Count Anagrams"
	},
	"version" : 
	{
		"major" : 2,
		"minor" : 5
	}
}
